harmony_device/Attribute.py
harmony_device/HarmonyClientRequestHandler.py
harmony_device/__init__.py
harmony_device/app.py
harmony_device/harmony.py
harmony_device-0.0.8.dist-info/LICENSE
harmony_device-0.0.8.dist-info/METADATA
harmony_device-0.0.8.dist-info/WHEEL
harmony_device-0.0.8.dist-info/top_level.txt
harmony_device-0.0.8.dist-info/RECORD
