Metadata-Version: 2.1
Name: harmony-device
Version: 0.0.8
Summary: Harmony - A standard protocol for controlling IoT devices
Home-page: https://github.com/naclcaleb/Harmony
Author: Caleb Hester
Author-email: naclcaleb@gmail.com
License: UNKNOWN
Platform: UNKNOWN
Classifier: Programming Language :: Python :: 3
Classifier: License :: OSI Approved :: MIT License
Classifier: Operating System :: OS Independent
Requires-Python: >=3.6
